README.rst
setup.py
as3/__init__.py
as3/as3.py
as3.egg-info/PKG-INFO
as3.egg-info/SOURCES.txt
as3.egg-info/dependency_links.txt
as3.egg-info/requires.txt
as3.egg-info/top_level.txt