Metadata-Version: 1.0
Name: as3
Version: 1.1
Summary: This is a Python module to easily use the F5 AS3 deployment method
Home-page: https://pypi.python.org/pypi?:action=display&name=as3&version=1.1
Author: Pete White
Author-email: pwhite@f5.com
License: PSF
Platform: UNKNOWN
